{
  "active": true,
  "before": false,
  "description": "new fix script",
  "flush_cache": false,
  "name": "newFix Script11",
  "record_for_rollback": false,
  "run_once": true,
  "script": {
    "____see": "sn\\Global\\Fix Script\\active_true\\newFix Script11.js"
  },
  "sys_class_name": "sys_script_fix",
  "sys_created_by": "admAdarsh",
  "sys_created_on": "2020-01-03 08:19:52",
  "sys_id": "58572b261b82c8d000584225bd4bcb79",
  "sys_mod_count": 1,
  "sys_name": "newFix Script11",
  "sys_package": "global",
  "sys_policy": null,
  "sys_scope": "global",
  "sys_update_name": "sys_script_fix_58572b261b82c8d000584225bd4bcb79",
  "sys_updated_by": "admAdarsh",
  "sys_updated_on": "2020-01-03 08:19:59",
  "unloadable": false
}
